qadence_model/__init__.py
qadence_model/types.py
qadence_model/models/__init__.py
qadence_model/models/parameters.py
qadence_model/models/qcnn_model.py
qadence_model/models/qnn_config.py
qadence_model/models/qnn_constructors.py
qadence_model/models/qnn_model.py
qadence_model/models/qnn_utils.py
qadence_model/optimizers/__init__.py
qadence_model/optimizers/qfi.py
qadence_model/optimizers/qng.py
qadence_model/optimizers/spsa.py
qadence_model/optimizers/utils.py
qadence_model-1.0.1.dist-info/METADATA
qadence_model-1.0.1.dist-info/WHEEL
qadence_model-1.0.1.dist-info/licenses/LICENSE
qadence_model-1.0.1.dist-info/RECORD
