Metadata-Version: 2.4
Name: qadence-model
Version: 1.0.1
Summary: Python package that provides quantum models for quantum machine learning features in Qadence.
Author-email: Mario Dagrada <mario.dagrada@pasqal.com>, Roland Guichard <roland.guichard@pasqal.com>, João Moutinho <joao.moutinho@pasqal.com>, Vincent Elfving <vincent.elfving@pasqal.com>, Dominik Seitz <dominik.seitz@pasqal.com>, Niklas Heim <niklas.heim@pasqal.com>, Ignacio Fernández Graña <ignacio.fernandez-grana@pasqal.com>, Manu Lahariya <manu.lahariya@pasqal.com>, Daniele Cucurachi <daniele.cucurachi@pasqal.com>, Sungwoo Ahn <sungwoo.ahn@pasqal.com>
License: Apache 2.0
License-File: LICENSE
Keywords: quantum
Classifier: License :: OSI Approved :: Apache Software License
Classifier: Programming Language :: Python
Classifier: Programming Language :: Python :: 3.9
Classifier: Programming Language :: Python :: 3.10
Classifier: Programming Language :: Python :: 3.11
Classifier: Programming Language :: Python :: 3.12
Classifier: Programming Language :: Python :: 3.13
Classifier: Programming Language :: Python :: Implementation :: CPython
Classifier: Programming Language :: Python :: Implementation :: PyPy
Requires-Python: <3.14,>=3.9
Requires-Dist: perceptrain[mlflow]
Requires-Dist: qadence[horqrux,pulser]
Requires-Dist: torch
